htQuant/__init__.py
htQuant/htData/__init__.py
htQuant/htData/config/__init__.py
htQuant/htData/config/settings.py
htQuant/htData/http/__init__.py
htQuant/htData/http/client.py
htQuant/htData/models/__init__.py
htQuant/htData/models/market_data.py
htQuant/utils/__init__.py
htQuant/utils/hosts.py
htquant-0.1.3.dist-info/METADATA
htquant-0.1.3.dist-info/WHEEL
htquant-0.1.3.dist-info/RECORD
