Metadata-Version: 2.4
Name: htQuant
Version: 0.1.3
Summary: htQuant 是以 Python 库的形式提供策略交易所需要的行情和相关的 API 接口
Author: htQuant Team
Keywords: data,finance,http,kafka,sdk,streaming
Requires-Python: >=3.8
Requires-Dist: confluent-kafka>=2.12.1
Requires-Dist: httpx>=0.25.0
Requires-Dist: pydantic-settings>=2.0.0
Requires-Dist: pydantic>=2.0.0
Requires-Dist: tenacity>=8.2.0
Provides-Extra: dev
Requires-Dist: mypy>=1.5.0; extra == 'dev'
Requires-Dist: pytest-asyncio>=0.21.0; extra == 'dev'
Requires-Dist: pytest-cov>=4.1.0; extra == 'dev'
Requires-Dist: pytest-mock>=3.11.0; extra == 'dev'
Requires-Dist: pytest>=7.4.0; extra == 'dev'
Requires-Dist: ruff>=0.1.0; extra == 'dev'
Provides-Extra: docs
Requires-Dist: mdx-truly-sane-lists>=1.3; extra == 'docs'
Requires-Dist: mkdocs-static-i18n>=1.0.0; extra == 'docs'
Requires-Dist: mkdocs>=1.5.0; extra == 'docs'
